{
  "global": {
    "baseSpace": {
      "$type": "spacing",
      "$value": "4"
    },
    "space-1": {
      "$type": "spacing",
      "$value": "{baseSpace}"
    },
    "space-2": {
      "$type": "spacing",
      "$value": "{baseSpace} *2"
    },
    "space-3": {
      "$type": "spacing",
      "$value": "{baseSpace} *3"
    },
    "space-4": {
      "$type": "spacing",
      "$value": "{baseSpace} *4"
    },
    "space-5": {
      "$type": "spacing",
      "$value": "{baseSpace} *5"
    },
    "Black": {
      "$type": "color",
      "$value": "#000"
    },
    "White": {
      "$type": "color",
      "$value": "#fff"
    },
    "Orange": {
      "$type": "color",
      "$value": "#FF9B17"
    },
    "Accent": {
      "$type": "color",
      "$value": "#74B3FF"
    },
    "radius-L": {
      "$type": "borderRadius",
      "$value": "8"
    },
    "base": {
      "$type": "fontSizes",
      "$value": "1.333"
    },
    "root": {
      "$type": "fontSizes",
      "$value": "14"
    },
    "medium": {
      "$type": "fontSizes",
      "$value": "{root}"
    },
    "Large": {
      "$type": "fontSizes",
      "$value": "{medium} * {base}"
    },
    "X-Large": {
      "$type": "fontSizes",
      "$value": "{Large} * {base}"
    },
    "Smail": {
      "$type": "fontSizes",
      "$value": "{medium} / {base}"
    }
  },
  "light": {
    "seccondary": {
      "$type": "color",
      "$value": "{Black}"
    }
  },
  "dark": {
    "seccondary": {
      "$type": "color",
      "$value": "{White}"
    }
  },
  "$themes": [],
  "$metadata": {
    "tokenSetOrder": [
      "global",
      "light",
      "dark"
    ]
  }
}